camci/__init__.py
camci/configuration.py
camci/data/__init__.py
camci/data/base.py
camci/data/contract.py
camci/data/sources/__init__.py
camci/data/sources/activedata/__init__.py
camci/data/sources/activedata/queries/push_revisions.query
camci/data/sources/activedata/queries/push_tasks_from_treeherder.query
camci/data/sources/activedata/queries/push_tasks_tags_from_task.query
camci/data/sources/activedata/queries/push_test_groups_from_unittest.query
camci/data/sources/treeherder/__init__.py
camci/errors.py
camci/push.py
camci/queries/group_durations.query
camci/task.py
camci/util/__init__.py
camci/util/cache_stores.py
camci/util/hgmo.py
camci/util/logging.py
camci/util/req.py
camci/util/taskcluster.py
camci/util/yaml.py
camci-1.8.1.dist-info/LICENSE
camci-1.8.1.dist-info/WHEEL
camci-1.8.1.dist-info/METADATA
camci-1.8.1.dist-info/RECORD
