Metadata-Version: 2.1
Name: camci
Version: 1.8.1
Summary: 
Author: Andrew Halberstadt
Author-email: ahal@mozilla.com
Requires-Python: >=3.7,<4.0
Classifier: Programming Language :: Python :: 3
Classifier: Programming Language :: Python :: 3.7
Classifier: Programming Language :: Python :: 3.8
Requires-Dist: adr (>=0.19,<0.20)
Requires-Dist: appdirs (>=1.4.4,<2.0.0)
Requires-Dist: boto3 (>=1.14.20,<2.0.0)
Requires-Dist: cachy (>=0.3.0,<0.4.0)
Requires-Dist: flake8 (>=3.8.3,<4.0.0)
Requires-Dist: loguru (>=0.5.1,<0.6.0)
Requires-Dist: python3-memcached (>=1.51,<2.0)
Requires-Dist: redis (>=3.5.3,<4.0.0)
Requires-Dist: requests (>=2.24.0,<3.0.0)
Requires-Dist: taskcluster_urls (>=12.1,<14.0)
Requires-Dist: tomlkit (>=0.6.0,<0.7.0)
Requires-Dist: voluptuous (>=0.11.7,<0.12.0)
Requires-Dist: zstandard (>=0.14.0,<0.15.0)
